nmrstar_xml/__init__.py
nmrstar_xml/main.py
nmrstar_xml/starxml.py
nmrstar_xml/test_NMRStarXml.py
nmrstar_xml/translate.py
nmrstar_xml/xmlstar.py
nmrstar_xml-1.0.2.dist-info/LICENSE
nmrstar_xml-1.0.2.dist-info/METADATA
nmrstar_xml-1.0.2.dist-info/WHEEL
nmrstar_xml-1.0.2.dist-info/entry_points.txt
nmrstar_xml-1.0.2.dist-info/top_level.txt
nmrstar_xml-1.0.2.dist-info/RECORD
