Metadata-Version: 2.1
Name: nmrstar_xml
Version: 1.0.2
Summary: Bidirectional conversion of NMRSTAR to XML
Author: Gerard
Author-email: gweatherby@uchc.edu
License: MIT
Project-URL: Homepage, https://github.com/NMRbox/nmrstar_xml.git
Keywords: NMRSTAR,XML
Classifier: Programming Language :: Python :: 3
Classifier: License :: OSI Approved :: MIT License
Classifier: Operating System :: OS Independent
Requires-Python: >=3.8
License-File: LICENSE
Requires-Dist: lxml
Requires-Dist: pynmrstar
